geode_hybrid_geosciences/__init__.py
geode_hybrid_geosciences/__init__.pyi
geode_hybrid_geosciences/pillar.py
geode_hybrid_geosciences/pillar.pyi
geode_hybrid_geosciences/py.typed
geode_hybrid_geosciences/lib64/__init__.pyi
geode_hybrid_geosciences/lib64/geode_hybrid_geosciences_py_pillar.cpython-312-x86_64-linux-gnu.so
geode_hybrid_geosciences/lib64/geode_hybrid_geosciences_py_pillar.pyi
geode_hybrid_geosciences/lib64/libGeode-Hybrid_Geosciences_pillar.so
geode_hybrid_geosciences-1.11.4.dist-info/METADATA
geode_hybrid_geosciences-1.11.4.dist-info/WHEEL
geode_hybrid_geosciences-1.11.4.dist-info/top_level.txt
geode_hybrid_geosciences-1.11.4.dist-info/RECORD
