Metadata-Version: 2.4
Name: Geode-Hybrid_Geosciences
Version: 1.11.4
Summary: Geosciences Hybrid  Geode-solutions  module
Author-email: Geode-solutions <contact@geode-solutions.com>
License: Proprietary
Requires-Python: <3.13,>=3.9
Requires-Dist: geode-background==9.*,>=9.9.6
Requires-Dist: geode-common==33.*,>=33.16.4
Requires-Dist: geode-conversion==6.*,>=6.5.10
Requires-Dist: opengeode-core==15.*,>=15.30.16
Requires-Dist: opengeode-geosciences==9.*,>=9.5.7
Requires-Dist: opengeode-inspector==6.*,>=6.8.15
